hystoc/cn_utils.py
hystoc/confusion_networks.py
hystoc/hystoc_confidences.py
hystoc/hystoc_fusion.py
hystoc/io_utils.py
hystoc-0.1.1.dist-info/LICENSE
hystoc-0.1.1.dist-info/METADATA
hystoc-0.1.1.dist-info/WHEEL
hystoc-0.1.1.dist-info/entry_points.txt
hystoc-0.1.1.dist-info/top_level.txt
hystoc-0.1.1.dist-info/RECORD
