Metadata-Version: 2.1
Name: hystoc
Version: 0.1.1
Summary: Toolkit for obtaining word-level confidences
Author-email: Karel Beneš <ibenes@fit.vutbr.cz>
License: MIT License
Project-URL: repository, https://github.com/BUTSpeechFIT/hystoc
Keywords: Confidence estimation,ASR
Classifier: Programming Language :: Python :: 3
Classifier: License :: OSI Approved :: MIT License
Classifier: Operating System :: OS Independent
Requires-Python: >=3.6
License-File: LICENSE
Requires-Dist: numpy
